LICENSE
MANIFEST.in
README
setup.py
anyit/__init__.py
anyit.djattributes.egg-info/PKG-INFO
anyit.djattributes.egg-info/SOURCES.txt
anyit.djattributes.egg-info/dependency_links.txt
anyit.djattributes.egg-info/top_level.txt
anyit/djattributes/__init__.py
anyit/djattributes/manage.py
anyit/djattributes/settings.py
anyit/djattributes/urls.py
anyit/djattributes/attributes/__init__.py
anyit/djattributes/attributes/fields.py
anyit/djattributes/attributes/models.py
anyit/djattributes/attributes/tests.py
anyit/djattributes/attributes/views.py