Metadata-Version: 1.0
Name: anyit.djattributes
Version: 0.2.5
Summary: Attributes for django models in a JQuery inspired syntax.
Home-page: UNKNOWN
Author: Jan Hoehn
Author-email: jan@anyit.de
License: BSD
Keywords: django atributes generic
Platform: UNKNOWN
Classifier: Development Status :: 4 - Beta
Classifier: Framework :: Django
Classifier: Intended Audience :: Developers
Classifier: License :: OSI Approved :: BSD License
Classifier: Operating System :: OS Independent
Classifier: Programming Language :: Python
Classifier: Topic :: Internet :: WWW/HTTP
